myro
setup.cfg
setup.py
myro/__init__.py
myro/chat.py
myro/chuck.py
myro/conx.py
myro/graphics.py
myro/intelhex.py
myro/media.py
myro/piano.py
myro/simulator.py
myro/speech.py
myro/system.py
myro/system2.py
myro/widgets.py
myro.egg-info/PKG-INFO
myro.egg-info/SOURCES.txt
myro.egg-info/dependency_links.txt
myro.egg-info/requires.txt
myro.egg-info/top_level.txt
myro/globvars/__init__.py
myro/robots/__init__.py
myro/robots/device.py
myro/robots/dongle.py
myro/robots/epuck.py
myro/robots/fluke.py
myro/robots/roomba.py
myro/robots/scribbler.py
myro/robots/scribbler2.py
myro/robots/simulator.py
myro/robots/surveyor.py
myro/robots/symbolic.py
myro/worlds/MyroWorld.py
myro/worlds/__init__.py